{
  "date": "18/03/2026",
  "zones": {
    "BASI A1": {
      "oggi": "yellow",
      "rischio_oggi": "Idrogeologico",
      "domani": "yellow",
      "rischio_domani": "Idrogeologico"
    },
    "BASI A2": {
      "oggi": "yellow",
      "rischio_oggi": "Idrogeologico",
      "domani": "yellow",
      "rischio_domani": "Idrogeologico"
    },
    "BASI B": {
      "oggi": "yellow",
      "rischio_oggi": "Idrogeologico",
      "domani": "yellow",
      "rischio_domani": "Idrogeologico"
    },
    "BASI C": {
      "oggi": "yellow",
      "rischio_oggi": "Idrogeologico",
      "domani": "yellow",
      "rischio_domani": "Idrogeologico"
    },
    "BASI D": {
      "oggi": "yellow",
      "rischio_oggi": "Idrogeologico",
      "domani": "yellow",
      "rischio_domani": "Idrogeologico"
    },
    "BASI E1": {
      "oggi": "yellow",
      "rischio_oggi": "Idrogeologico + Idraulico",
      "domani": "yellow",
      "rischio_domani": "Idrogeologico + Idraulico"
    },
    "BASI E2": {
      "oggi": "yellow",
      "rischio_oggi": "Idrogeologico + Idraulico",
      "domani": "yellow",
      "rischio_domani": "Idrogeologico + Idraulico"
    }
  }
}